arm_text_detection/_init_.py
arm_text_detection/detection.py
arm_text_detection-0.4.dist-info/METADATA
arm_text_detection-0.4.dist-info/WHEEL
arm_text_detection-0.4.dist-info/top_level.txt
arm_text_detection-0.4.dist-info/RECORD
