Metadata-Version: 2.1
Name: arm_text_detection
Version: 0.4
Summary: Detection armenian text
Author: Renaxit
Author-email: renalshagin777@gmail.com
Classifier: Programming Language :: Python :: 3
Classifier: License :: OSI Approved :: MIT License
Classifier: Operating System :: OS Independent
Requires-Python: >=3.6
